explx/__init__.py
explx-0.0.4.dist-info/licenses/LICENSE
explx-0.0.4.dist-info/METADATA
explx-0.0.4.dist-info/WHEEL
explx-0.0.4.dist-info/top_level.txt
explx-0.0.4.dist-info/RECORD
