Metadata-Version: 2.4
Name: explx
Version: 0.0.4
Summary: A Python package for exploratory data analysis
Author-email: Farzad Asgari <khufarzadasgari@gmail.com>
License-Expression: MIT
Project-URL: Homepage, https://github.com/farzadasgari/explx
Project-URL: Repository, https://github.com/farzadasgari/explx
Project-URL: Bug Tracker, https://github.com/farzadasgari/explx/issues
Project-URL: Changelog, https://github.com/farzadasgari/explx/releases
Keywords: python,data,data analysis,exploratory data analysis,explx
Classifier: Development Status :: 3 - Alpha
Classifier: Intended Audience :: Science/Research
Classifier: Intended Audience :: Other Audience
Classifier: Programming Language :: Python :: 3
Classifier: Programming Language :: Python :: 3.8
Classifier: Programming Language :: Python :: 3.9
Classifier: Programming Language :: Python :: 3.10
Classifier: Programming Language :: Python :: 3.11
Classifier: Programming Language :: Python :: 3.12
Classifier: Operating System :: OS Independent
Requires-Python: >=3.8
License-File: LICENSE
Dynamic: license-file
